README.rst
setup.py
ratneshpy/__init__.py
ratneshpy/core.py
ratneshpy.egg-info/PKG-INFO
ratneshpy.egg-info/SOURCES.txt
ratneshpy.egg-info/dependency_links.txt
ratneshpy.egg-info/requires.txt
ratneshpy.egg-info/top_level.txt