Metadata-Version: 1.1
Name: ratneshpy
Version: 0.1.2
Summary: Ratnesh python package for work
Home-page: https://github.com/imratnesh/ratneshpy
Author: Ratnesh Kushwaha
Author-email: rat.kush@gmail.com
License: MIT
Platform: UNKNOWN
Classifier: Development Status :: 2 - Pre-Alpha
Classifier: License :: OSI Approved :: MIT License
Classifier: Programming Language :: Python
Classifier: Programming Language :: Python :: 2
Classifier: Programming Language :: Python :: 2.7
Classifier: Programming Language :: Python :: 3
Classifier: Programming Language :: Python :: 3.4
Classifier: Programming Language :: Python :: 3.5
Classifier: Programming Language :: Python :: 3.6
Classifier: Programming Language :: Python :: 3.7
